tox2travis/__init__.py
tox2travis/__main__.py
tox2travis/tox2travis.py
tox2travis/version.py
tox2travis-1.1.dist-info/LICENSE
tox2travis-1.1.dist-info/METADATA
tox2travis-1.1.dist-info/WHEEL
tox2travis-1.1.dist-info/entry_points.txt
tox2travis-1.1.dist-info/top_level.txt
tox2travis-1.1.dist-info/RECORD
