Metadata-Version: 2.1
Name: tox2travis
Version: 1.1
Summary: Automatically generate .travis.yml or GitHub actions workflow .yml from tox.ini
Home-page: http://github.com/mineo/tox2travis
Author: Wieland Hoffmann
Author-email: themineo@gmail.com
License: MIT
Download-URL: https://github.com/mineo/tox2travis/tarball/master
Platform: UNKNOWN
Classifier: Development Status :: 4 - Beta
Classifier: License :: OSI Approved :: MIT License
Classifier: Natural Language :: English
Classifier: Operating System :: OS Independent
Classifier: Programming Language :: Python :: 3.6
Requires-Python: >=3.6
Requires-Dist: click
Requires-Dist: tox
Provides-Extra: docs
Requires-Dist: sphinx ; extra == 'docs'
